zendo/__init__.py
zendo/app.py
zendo/auth.py
zendo/config.py
zendo/constants.py
zendo/main.py
zendo/models.py
zendo/assets/bootstrap-custom.css
zendo/assets/bootstrap-custom.css.map
zendo/assets/callbacks.js
zendo/assets/default.css
zendo/assets/default.js
zendo/components/__init__.py
zendo/components/chat.py
zendo/components/login.py
zendo/components/navbar.py
zendo/components/register.py
zendo/components/timer.py
zendo/layouts/__init__.py
zendo/layouts/auth_layout.py
zendo/layouts/main_layout.py
zendo/services/__init__.py
zendo/services/applet_state.py
zendo-0.0.1.dist-info/METADATA
zendo-0.0.1.dist-info/WHEEL
zendo-0.0.1.dist-info/entry_points.txt
zendo-0.0.1.dist-info/licenses/LICENSE.txt
zendo-0.0.1.dist-info/RECORD
